{
  "Female": [
    {
      "Age": 0,
      "SU": 2,
      "UFrom": 2.1,
      "UTo": 2.3,
      "NFrom": 2.4,
      "NTo": 4.2,
      "OW": 4.3
    },
    {
      "Age": 1,
      "SU": 2.7,
      "UFrom": 2.8,
      "UTo": 3.1,
      "NFrom": 3.2,
      "NTo": 5.5,
      "OW": 5.6
    },
    {
      "Age": 2,
      "SU": 3.4,
      "UFrom": 3.5,
      "UTo": 3.8,
      "NFrom": 3.9,
      "NTo": 6.6,
      "OW": 6.7
    },
    {
      "Age": 3,
      "SU": 4,
      "UFrom": 4.1,
      "UTo": 4.4,
      "NFrom": 4.5,
      "NTo": 7.5,
      "OW": 7.6
    },
    {
      "Age": 4,
      "SU": 4.4,
      "UFrom": 4.5,
      "UTo": 4.9,
      "NFrom": 5,
      "NTo": 8.2,
      "OW": 8.3
    },
    {
      "Age": 5,
      "SU": 4.8,
      "UFrom": 4.9,
      "UTo": 5.3,
      "NFrom": 5.4,
      "NTo": 8.8,
      "OW": 8.9
    },
    {
      "Age": 6,
      "SU": 5.1,
      "UFrom": 5.2,
      "UTo": 5.6,
      "NFrom": 5.7,
      "NTo": 9.3,
      "OW": 9.4
    },
    {
      "Age": 7,
      "SU": 5.3,
      "UFrom": 5.4,
      "UTo": 5.9,
      "NFrom": 6,
      "NTo": 9.8,
      "OW": 9.9
    },
    {
      "Age": 8,
      "SU": 5.6,
      "UFrom": 5.7,
      "UTo": 6.2,
      "NFrom": 6.3,
      "NTo": 10.2,
      "OW": 10.3
    },
    {
      "Age": 9,
      "SU": 5.8,
      "UFrom": 5.9,
      "UTo": 6.4,
      "NFrom": 6.5,
      "NTo": 10.5,
      "OW": 10.6
    },
    {
      "Age": 10,
      "SU": 5.9,
      "UFrom": 6,
      "UTo": 6.6,
      "NFrom": 6.7,
      "NTo": 10.9,
      "OW": 11
    },
    {
      "Age": 11,
      "SU": 6.1,
      "UFrom": 6.2,
      "UTo": 6.8,
      "NFrom": 6.9,
      "NTo": 11.2,
      "OW": 11.3
    },
    {
      "Age": 12,
      "SU": 6.3,
      "UFrom": 6.4,
      "UTo": 6.9,
      "NFrom": 7,
      "NTo": 11.5,
      "OW": 11.6
    },
    {
      "Age": 13,
      "SU": 6.4,
      "UFrom": 6.5,
      "UTo": 7.1,
      "NFrom": 7.2,
      "NTo": 11.8,
      "OW": 11.9
    },
    {
      "Age": 14,
      "SU": 6.6,
      "UFrom": 6.7,
      "UTo": 7.3,
      "NFrom": 7.4,
      "NTo": 12.1,
      "OW": 12.2
    },
    {
      "Age": 15,
      "SU": 6.7,
      "UFrom": 6.8,
      "UTo": 7.5,
      "NFrom": 7.6,
      "NTo": 12.4,
      "OW": 12.5
    },
    {
      "Age": 16,
      "SU": 6.9,
      "UFrom": 7,
      "UTo": 7.6,
      "NFrom": 7.7,
      "NTo": 12.6,
      "OW": 12.7
    },
    {
      "Age": 17,
      "SU": 7,
      "UFrom": 7.1,
      "UTo": 7.8,
      "NFrom": 7.9,
      "NTo": 12.9,
      "OW": 13
    },
    {
      "Age": 18,
      "SU": 7.2,
      "UFrom": 7.3,
      "UTo": 8,
      "NFrom": 8.1,
      "NTo": 13.2,
      "OW": 13.3
    },
    {
      "Age": 19,
      "SU": 7.3,
      "UFrom": 7.4,
      "UTo": 8.1,
      "NFrom": 8.2,
      "NTo": 13.5,
      "OW": 13.6
    },
    {
      "Age": 20,
      "SU": 7.5,
      "UFrom": 7.6,
      "UTo": 8.3,
      "NFrom": 8.4,
      "NTo": 13.7,
      "OW": 13.8
    },
    {
      "Age": 21,
      "SU": 7.6,
      "UFrom": 7.7,
      "UTo": 8.5,
      "NFrom": 8.6,
      "NTo": 14,
      "OW": 14.1
    },
    {
      "Age": 22,
      "SU": 7.8,
      "UFrom": 7.9,
      "UTo": 8.6,
      "NFrom": 8.7,
      "NTo": 14.3,
      "OW": 14.4
    },
    {
      "Age": 23,
      "SU": 7.9,
      "UFrom": 8,
      "UTo": 8.8,
      "NFrom": 8.9,
      "NTo": 14.6,
      "OW": 14.7
    },
    {
      "Age": 24,
      "SU": 8.1,
      "UFrom": 8.2,
      "UTo": 8.9,
      "NFrom": 9,
      "NTo": 14.8,
      "OW": 14.9
    },
    {
      "Age": 25,
      "SU": 8.2,
      "UFrom": 8.3,
      "UTo": 9.1,
      "NFrom": 9.2,
      "NTo": 15.1,
      "OW": 15.2
    },
    {
      "Age": 26,
      "SU": 8.4,
      "UFrom": 8.5,
      "UTo": 9.3,
      "NFrom": 9.4,
      "NTo": 15.4,
      "OW": 15.5
    },
    {
      "Age": 27,
      "SU": 8.5,
      "UFrom": 8.6,
      "UTo": 9.4,
      "NFrom": 9.5,
      "NTo": 15.7,
      "OW": 15.8
    },
    {
      "Age": 28,
      "SU": 8.6,
      "UFrom": 8.7,
      "UTo": 9.6,
      "NFrom": 9.7,
      "NTo": 16,
      "OW": 16.1
    },
    {
      "Age": 29,
      "SU": 8.8,
      "UFrom": 8.9,
      "UTo": 9.7,
      "NFrom": 9.8,
      "NTo": 16.2,
      "OW": 16.3
    },
    {
      "Age": 30,
      "SU": 8.9,
      "UFrom": 9,
      "UTo": 9.9,
      "NFrom": 10,
      "NTo": 16.5,
      "OW": 16.6
    },
    {
      "Age": 31,
      "SU": 9,
      "UFrom": 9.1,
      "UTo": 10,
      "NFrom": 10.1,
      "NTo": 16.8,
      "OW": 16.9
    },
    {
      "Age": 32,
      "SU": 9.1,
      "UFrom": 9.2,
      "UTo": 10.2,
      "NFrom": 10.3,
      "NTo": 17.1,
      "OW": 17.2
    },
    {
      "Age": 33,
      "SU": 9.3,
      "UFrom": 9.4,
      "UTo": 10.3,
      "NFrom": 10.4,
      "NTo": 17.3,
      "OW": 17.4
    },
    {
      "Age": 34,
      "SU": 9.4,
      "UFrom": 9.5,
      "UTo": 10.4,
      "NFrom": 10.5,
      "NTo": 17.6,
      "OW": 17.7
    },
    {
      "Age": 35,
      "SU": 9.5,
      "UFrom": 9.6,
      "UTo": 10.6,
      "NFrom": 10.7,
      "NTo": 17.9,
      "OW": 18
    },
    {
      "Age": 36,
      "SU": 9.6,
      "UFrom": 9.7,
      "UTo": 10.7,
      "NFrom": 10.8,
      "NTo": 18.1,
      "OW": 18.2
    },
    {
      "Age": 37,
      "SU": 9.7,
      "UFrom": 9.8,
      "UTo": 10.8,
      "NFrom": 10.9,
      "NTo": 18.4,
      "OW": 18.5
    },
    {
      "Age": 38,
      "SU": 9.8,
      "UFrom": 9.9,
      "UTo": 11,
      "NFrom": 11.1,
      "NTo": 18.7,
      "OW": 18.8
    },
    {
      "Age": 39,
      "SU": 9.9,
      "UFrom": 10,
      "UTo": 11.1,
      "NFrom": 11.2,
      "NTo": 19,
      "OW": 19.1
    },
    {
      "Age": 40,
      "SU": 10.1,
      "UFrom": 10.2,
      "UTo": 11.2,
      "NFrom": 11.3,
      "NTo": 19.2,
      "OW": 19.3
    },
    {
      "Age": 41,
      "SU": 10.2,
      "UFrom": 10.3,
      "UTo": 11.4,
      "NFrom": 11.5,
      "NTo": 19.5,
      "OW": 19.6
    },
    {
      "Age": 42,
      "SU": 10.3,
      "UFrom": 10.4,
      "UTo": 11.5,
      "NFrom": 11.6,
      "NTo": 19.8,
      "OW": 19.9
    },
    {
      "Age": 43,
      "SU": 10.4,
      "UFrom": 10.5,
      "UTo": 11.6,
      "NFrom": 11.7,
      "NTo": 20.1,
      "OW": 20.2
    },
    {
      "Age": 44,
      "SU": 10.5,
      "UFrom": 10.6,
      "UTo": 11.7,
      "NFrom": 11.8,
      "NTo": 20.4,
      "OW": 20.5
    },
    {
      "Age": 45,
      "SU": 10.6,
      "UFrom": 10.7,
      "UTo": 11.9,
      "NFrom": 12,
      "NTo": 20.7,
      "OW": 20.8
    },
    {
      "Age": 46,
      "SU": 10.7,
      "UFrom": 10.8,
      "UTo": 12,
      "NFrom": 12.1,
      "NTo": 20.9,
      "OW": 21
    },
    {
      "Age": 47,
      "SU": 10.8,
      "UFrom": 10.9,
      "UTo": 12.1,
      "NFrom": 12.2,
      "NTo": 21.2,
      "OW": 21.3
    },
    {
      "Age": 48,
      "SU": 10.9,
      "UFrom": 11,
      "UTo": 12.2,
      "NFrom": 12.3,
      "NTo": 21.5,
      "OW": 21.6
    },
    {
      "Age": 49,
      "SU": 11,
      "UFrom": 11.1,
      "UTo": 12.3,
      "NFrom": 12.4,
      "NTo": 21.8,
      "OW": 21.9
    },
    {
      "Age": 50,
      "SU": 11.1,
      "UFrom": 11.2,
      "UTo": 12.4,
      "NFrom": 12.5,
      "NTo": 22.1,
      "OW": 22.2
    },
    {
      "Age": 51,
      "SU": 11.2,
      "UFrom": 11.3,
      "UTo": 12.6,
      "NFrom": 12.7,
      "NTo": 22.4,
      "OW": 22.5
    },
    {
      "Age": 52,
      "SU": 11.3,
      "UFrom": 11.4,
      "UTo": 12.7,
      "NFrom": 12.8,
      "NTo": 22.6,
      "OW": 22.7
    },
    {
      "Age": 53,
      "SU": 11.4,
      "UFrom": 11.5,
      "UTo": 12.8,
      "NFrom": 12.9,
      "NTo": 22.9,
      "OW": 23
    },
    {
      "Age": 54,
      "SU": 11.5,
      "UFrom": 11.6,
      "UTo": 12.9,
      "NFrom": 13,
      "NTo": 23.2,
      "OW": 23.3
    },
    {
      "Age": 55,
      "SU": 11.6,
      "UFrom": 11.7,
      "UTo": 13.1,
      "NFrom": 13.2,
      "NTo": 23.5,
      "OW": 23.6
    },
    {
      "Age": 56,
      "SU": 11.7,
      "UFrom": 11.8,
      "UTo": 13.2,
      "NFrom": 13.3,
      "NTo": 23.8,
      "OW": 23.9
    },
    {
      "Age": 57,
      "SU": 11.8,
      "UFrom": 11.9,
      "UTo": 13.3,
      "NFrom": 13.4,
      "NTo": 24.1,
      "OW": 24.2
    },
    {
      "Age": 58,
      "SU": 11.9,
      "UFrom": 12,
      "UTo": 13.4,
      "NFrom": 13.5,
      "NTo": 24.4,
      "OW": 24.5
    },
    {
      "Age": 59,
      "SU": 12,
      "UFrom": 12.1,
      "UTo": 13.5,
      "NFrom": 13.6,
      "NTo": 24.6,
      "OW": 24.7
    },
    {
      "Age": 60,
      "SU": 12.1,
      "UFrom": 12.2,
      "UTo": 13.6,
      "NFrom": 13.7,
      "NTo": 24.7,
      "OW": 24.8
    },
    {
      "Age": 61,
      "SU": 12.4,
      "UFrom": 12.5,
      "UTo": 13.9,
      "NFrom": 14,
      "NTo": 24.8,
      "OW": 24.9
    },
    {
      "Age": 62,
      "SU": 12.5,
      "UFrom": 12.6,
      "UTo": 14,
      "NFrom": 14.1,
      "NTo": 25.1,
      "OW": 25.2
    },
    {
      "Age": 63,
      "SU": 12.6,
      "UFrom": 12.7,
      "UTo": 14.1,
      "NFrom": 14.2,
      "NTo": 25.4,
      "OW": 25.5
    },
    {
      "Age": 64,
      "SU": 12.7,
      "UFrom": 12.8,
      "UTo": 14.2,
      "NFrom": 14.3,
      "NTo": 25.6,
      "OW": 25.7
    },
    {
      "Age": 65,
      "SU": 12.8,
      "UFrom": 12.9,
      "UTo": 14.3,
      "NFrom": 14.4,
      "NTo": 25.9,
      "OW": 26
    },
    {
      "Age": 66,
      "SU": 12.9,
      "UFrom": 13,
      "UTo": 14.5,
      "NFrom": 14.6,
      "NTo": 26.2,
      "OW": 26.3
    },
    {
      "Age": 67,
      "SU": 13,
      "UFrom": 13.1,
      "UTo": 14.6,
      "NFrom": 14.7,
      "NTo": 26.5,
      "OW": 26.6
    },
    {
      "Age": 68,
      "SU": 13.1,
      "UFrom": 13.2,
      "UTo": 14.7,
      "NFrom": 14.8,
      "NTo": 26.7,
      "OW": 26.8
    },
    {
      "Age": 69,
      "SU": 13.2,
      "UFrom": 13.3,
      "UTo": 14.8,
      "NFrom": 14.9,
      "NTo": 27,
      "OW": 27.1
    },
    {
      "Age": 70,
      "SU": 13.3,
      "UFrom": 13.4,
      "UTo": 14.9,
      "NFrom": 15,
      "NTo": 27.3,
      "OW": 27.4
    },
    {
      "Age": 71,
      "SU": 13.4,
      "UFrom": 13.5,
      "UTo": 15.1,
      "NFrom": 15.2,
      "NTo": 27.6,
      "OW": 27.7
    }
  ],
  "Male": [
    {
      "Age": 0,
      "SU": 2.1,
      "UFrom": 2.2,
      "UTo": 2.4,
      "NFrom": 2.5,
      "NTo": 4.4,
      "OW": 4.5
    },
    {
      "Age": 1,
      "SU": 2.9,
      "UFrom": 3,
      "UTo": 3.3,
      "NFrom": 3.4,
      "NTo": 5.8,
      "OW": 5.9
    },
    {
      "Age": 2,
      "SU": 3.8,
      "UFrom": 3.9,
      "UTo": 4.2,
      "NFrom": 4.3,
      "NTo": 7.1,
      "OW": 7.2
    },
    {
      "Age": 3,
      "SU": 4.4,
      "UFrom": 4.5,
      "UTo": 4.9,
      "NFrom": 5,
      "NTo": 8,
      "OW": 8.1
    },
    {
      "Age": 4,
      "SU": 4.9,
      "UFrom": 5,
      "UTo": 5.5,
      "NFrom": 5.6,
      "NTo": 8.7,
      "OW": 8.8
    },
    {
      "Age": 5,
      "SU": 5.3,
      "UFrom": 5.4,
      "UTo": 5.9,
      "NFrom": 6,
      "NTo": 9.3,
      "OW": 9.4
    },
    {
      "Age": 6,
      "SU": 5.7,
      "UFrom": 5.8,
      "UTo": 6.3,
      "NFrom": 6.4,
      "NTo": 9.8,
      "OW": 9.9
    },
    {
      "Age": 7,
      "SU": 5.9,
      "UFrom": 6,
      "UTo": 6.6,
      "NFrom": 6.7,
      "NTo": 10.3,
      "OW": 10.4
    },
    {
      "Age": 8,
      "SU": 6.2,
      "UFrom": 6.3,
      "UTo": 6.8,
      "NFrom": 6.9,
      "NTo": 10.7,
      "OW": 10.8
    },
    {
      "Age": 9,
      "SU": 6.4,
      "UFrom": 6.5,
      "UTo": 7,
      "NFrom": 7.1,
      "NTo": 11,
      "OW": 11.1
    },
    {
      "Age": 10,
      "SU": 6.6,
      "UFrom": 6.7,
      "UTo": 7.3,
      "NFrom": 7.4,
      "NTo": 11.4,
      "OW": 11.5
    },
    {
      "Age": 11,
      "SU": 6.8,
      "UFrom": 6.9,
      "UTo": 7.5,
      "NFrom": 7.6,
      "NTo": 11.7,
      "OW": 11.8
    },
    {
      "Age": 12,
      "SU": 6.9,
      "UFrom": 7,
      "UTo": 7.6,
      "NFrom": 7.7,
      "NTo": 12,
      "OW": 12.1
    },
    {
      "Age": 13,
      "SU": 7.1,
      "UFrom": 7.2,
      "UTo": 7.8,
      "NFrom": 7.9,
      "NTo": 12.3,
      "OW": 12.4
    },
    {
      "Age": 14,
      "SU": 7.2,
      "UFrom": 7.3,
      "UTo": 8,
      "NFrom": 8.1,
      "NTo": 12.6,
      "OW": 13.2
    },
    {
      "Age": 15,
      "SU": 7.4,
      "UFrom": 7.5,
      "UTo": 8.2,
      "NFrom": 8.3,
      "NTo": 12.8,
      "OW": 12.9
    },
    {
      "Age": 16,
      "SU": 7.5,
      "UFrom": 7.6,
      "UTo": 8.3,
      "NFrom": 8.4,
      "NTo": 13.1,
      "OW": 13.2
    },
    {
      "Age": 17,
      "SU": 7.7,
      "UFrom": 7.8,
      "UTo": 8.5,
      "NFrom": 8.6,
      "NTo": 13.4,
      "OW": 13.5
    },
    {
      "Age": 18,
      "SU": 7.8,
      "UFrom": 7.9,
      "UTo": 8.7,
      "NFrom": 8.8,
      "NTo": 13.7,
      "OW": 13.8
    },
    {
      "Age": 19,
      "SU": 8,
      "UFrom": 8.1,
      "UTo": 8.8,
      "NFrom": 8.9,
      "NTo": 13.9,
      "OW": 14
    },
    {
      "Age": 20,
      "SU": 8.1,
      "UFrom": 8.2,
      "UTo": 9,
      "NFrom": 9.1,
      "NTo": 14.2,
      "OW": 14.3
    },
    {
      "Age": 21,
      "SU": 8.2,
      "UFrom": 8.3,
      "UTo": 9.1,
      "NFrom": 9.2,
      "NTo": 14.5,
      "OW": 14.6
    },
    {
      "Age": 22,
      "SU": 8.4,
      "UFrom": 8.5,
      "UTo": 9.3,
      "NFrom": 9.4,
      "NTo": 14.7,
      "OW": 14.8
    },
    {
      "Age": 23,
      "SU": 8.5,
      "UFrom": 8.6,
      "UTo": 9.4,
      "NFrom": 9.5,
      "NTo": 15,
      "OW": 15.1
    },
    {
      "Age": 24,
      "SU": 8.6,
      "UFrom": 8.7,
      "UTo": 9.6,
      "NFrom": 9.7,
      "NTo": 15.3,
      "OW": 15.4
    },
    {
      "Age": 25,
      "SU": 8.8,
      "UFrom": 8.9,
      "UTo": 9.7,
      "NFrom": 9.8,
      "NTo": 15.5,
      "OW": 15.6
    },
    {
      "Age": 26,
      "SU": 8.9,
      "UFrom": 9,
      "UTo": 9.9,
      "NFrom": 10,
      "NTo": 15.8,
      "OW": 15.9
    },
    {
      "Age": 27,
      "SU": 9,
      "UFrom": 9.1,
      "UTo": 10,
      "NFrom": 10.1,
      "NTo": 16.1,
      "OW": 16.2
    },
    {
      "Age": 28,
      "SU": 9.1,
      "UFrom": 9.2,
      "UTo": 10.1,
      "NFrom": 10.2,
      "NTo": 16.3,
      "OW": 16.4
    },
    {
      "Age": 29,
      "SU": 9.2,
      "UFrom": 9.3,
      "UTo": 10.3,
      "NFrom": 10.4,
      "NTo": 16.6,
      "OW": 16.7
    },
    {
      "Age": 30,
      "SU": 9.4,
      "UFrom": 9.5,
      "UTo": 10.4,
      "NFrom": 10.5,
      "NTo": 16.9,
      "OW": 17
    },
    {
      "Age": 31,
      "SU": 9.5,
      "UFrom": 9.6,
      "UTo": 10.6,
      "NFrom": 10.7,
      "NTo": 17.1,
      "OW": 17.2
    },
    {
      "Age": 32,
      "SU": 9.6,
      "UFrom": 9.7,
      "UTo": 10.7,
      "NFrom": 10.8,
      "NTo": 17.4,
      "OW": 17.5
    },
    {
      "Age": 33,
      "SU": 9.7,
      "UFrom": 9.8,
      "UTo": 10.8,
      "NFrom": 10.9,
      "NTo": 17.6,
      "OW": 17.7
    },
    {
      "Age": 34,
      "SU": 9.8,
      "UFrom": 9.9,
      "UTo": 10.9,
      "NFrom": 11,
      "NTo": 17.8,
      "OW": 17.9
    },
    {
      "Age": 35,
      "SU": 9.9,
      "UFrom": 10,
      "UTo": 11.1,
      "NFrom": 11.2,
      "NTo": 18.1,
      "OW": 18.2
    },
    {
      "Age": 36,
      "SU": 10,
      "UFrom": 10.1,
      "UTo": 11.2,
      "NFrom": 11.3,
      "NTo": 18.3,
      "OW": 18.4
    },
    {
      "Age": 37,
      "SU": 10.1,
      "UFrom": 10.2,
      "UTo": 11.3,
      "NFrom": 11.4,
      "NTo": 18.6,
      "OW": 18.7
    },
    {
      "Age": 38,
      "SU": 10.2,
      "UFrom": 10.3,
      "UTo": 11.4,
      "NFrom": 11.5,
      "NTo": 18.8,
      "OW": 18.9
    },
    {
      "Age": 39,
      "SU": 10.3,
      "UFrom": 10.4,
      "UTo": 11.5,
      "NFrom": 11.6,
      "NTo": 19,
      "OW": 19.1
    },
    {
      "Age": 40,
      "SU": 10.4,
      "UFrom": 10.5,
      "UTo": 11.7,
      "NFrom": 11.8,
      "NTo": 19.3,
      "OW": 19.4
    },
    {
      "Age": 41,
      "SU": 10.5,
      "UFrom": 10.6,
      "UTo": 11.8,
      "NFrom": 11.9,
      "NTo": 19.5,
      "OW": 19.6
    },
    {
      "Age": 42,
      "SU": 10.6,
      "UFrom": 10.7,
      "UTo": 11.9,
      "NFrom": 12,
      "NTo": 19.7,
      "OW": 19.8
    },
    {
      "Age": 43,
      "SU": 10.7,
      "UFrom": 10.8,
      "UTo": 12,
      "NFrom": 12.1,
      "NTo": 20,
      "OW": 20.1
    },
    {
      "Age": 44,
      "SU": 10.8,
      "UFrom": 10.9,
      "UTo": 12.1,
      "NFrom": 12.2,
      "NTo": 20.2,
      "OW": 20.3
    },
    {
      "Age": 45,
      "SU": 10.9,
      "UFrom": 11,
      "UTo": 12.3,
      "NFrom": 12.4,
      "NTo": 20.5,
      "OW": 20.6
    },
    {
      "Age": 46,
      "SU": 11,
      "UFrom": 11.1,
      "UTo": 12.4,
      "NFrom": 12.5,
      "NTo": 20.7,
      "OW": 20.8
    },
    {
      "Age": 47,
      "SU": 11.1,
      "UFrom": 11.2,
      "UTo": 12.5,
      "NFrom": 12.6,
      "NTo": 20.9,
      "OW": 21
    },
    {
      "Age": 48,
      "SU": 11.2,
      "UFrom": 11.3,
      "UTo": 12.6,
      "NFrom": 12.7,
      "NTo": 21.2,
      "OW": 21.3
    },
    {
      "Age": 49,
      "SU": 11.3,
      "UFrom": 11.4,
      "UTo": 12.7,
      "NFrom": 12.8,
      "NTo": 21.4,
      "OW": 21.5
    },
    {
      "Age": 50,
      "SU": 11.4,
      "UFrom": 11.5,
      "UTo": 12.8,
      "NFrom": 12.9,
      "NTo": 21.7,
      "OW": 21.8
    },
    {
      "Age": 51,
      "SU": 11.5,
      "UFrom": 11.6,
      "UTo": 13,
      "NFrom": 13.1,
      "NTo": 21.9,
      "OW": 22
    },
    {
      "Age": 52,
      "SU": 11.6,
      "UFrom": 11.7,
      "UTo": 13.1,
      "NFrom": 13.2,
      "NTo": 22.2,
      "OW": 22.3
    },
    {
      "Age": 53,
      "SU": 11.7,
      "UFrom": 11.8,
      "UTo": 13.2,
      "NFrom": 13.3,
      "NTo": 22.4,
      "OW": 22.5
    },
    {
      "Age": 54,
      "SU": 11.8,
      "UFrom": 11.9,
      "UTo": 13.3,
      "NFrom": 13.4,
      "NTo": 22.7,
      "OW": 22.8
    },
    {
      "Age": 55,
      "SU": 11.9,
      "UFrom": 12,
      "UTo": 13.4,
      "NFrom": 13.5,
      "NTo": 22.9,
      "OW": 23
    },
    {
      "Age": 56,
      "SU": 12,
      "UFrom": 12.1,
      "UTo": 13.5,
      "NFrom": 13.6,
      "NTo": 23.2,
      "OW": 23.3
    },
    {
      "Age": 57,
      "SU": 12.1,
      "UFrom": 12.2,
      "UTo": 13.6,
      "NFrom": 13.7,
      "NTo": 23.4,
      "OW": 23.5
    },
    {
      "Age": 58,
      "SU": 12.2,
      "UFrom": 12.3,
      "UTo": 13.7,
      "NFrom": 13.8,
      "NTo": 23.7,
      "OW": 23.8
    },
    {
      "Age": 59,
      "SU": 12.3,
      "UFrom": 12.4,
      "UTo": 13.9,
      "NFrom": 14,
      "NTo": 23.9,
      "OW": 24
    },
    {
      "Age": 60,
      "SU": 12.4,
      "UFrom": 12.5,
      "UTo": 14,
      "NFrom": 14.1,
      "NTo": 24.2,
      "OW": 24.3
    },
    {
      "Age": 61,
      "SU": 12.7,
      "UFrom": 12.8,
      "UTo": 14.3,
      "NFrom": 14.4,
      "NTo": 24.3,
      "OW": 24.4
    },
    {
      "Age": 62,
      "SU": 12.8,
      "UFrom": 12.9,
      "UTo": 14.4,
      "NFrom": 14.5,
      "NTo": 24.4,
      "OW": 24.5
    },
    {
      "Age": 63,
      "SU": 13,
      "UFrom": 13.1,
      "UTo": 14.5,
      "NFrom": 14.6,
      "NTo": 24.7,
      "OW": 24.8
    },
    {
      "Age": 64,
      "SU": 13.1,
      "UFrom": 13.2,
      "UTo": 14.7,
      "NFrom": 14.8,
      "NTo": 24.9,
      "OW": 25
    },
    {
      "Age": 65,
      "SU": 13.2,
      "UFrom": 13.3,
      "UTo": 14.8,
      "NFrom": 14.9,
      "NTo": 25.2,
      "OW": 25.3
    },
    {
      "Age": 66,
      "SU": 13.3,
      "UFrom": 13.4,
      "UTo": 14.9,
      "NFrom": 15,
      "NTo": 25.5,
      "OW": 25.6
    },
    {
      "Age": 67,
      "SU": 13.4,
      "UFrom": 13.5,
      "UTo": 15.1,
      "NFrom": 15.2,
      "NTo": 25.7,
      "OW": 25.8
    },
    {
      "Age": 68,
      "SU": 13.6,
      "UFrom": 13.7,
      "UTo": 15.2,
      "NFrom": 15.3,
      "NTo": 26,
      "OW": 26.1
    },
    {
      "Age": 69,
      "SU": 13.7,
      "UFrom": 13.8,
      "UTo": 15.3,
      "NFrom": 15.4,
      "NTo": 26.3,
      "OW": 26.4
    },
    {
      "Age": 70,
      "SU": 13.8,
      "UFrom": 13.9,
      "UTo": 15.5,
      "NFrom": 15.6,
      "NTo": 26.6,
      "OW": 26.7
    },
    {
      "Age": 71,
      "SU": 13.9,
      "UFrom": 14,
      "UTo": 15.6,
      "NFrom": 15.7,
      "NTo": 26.8,
      "OW": 26.9
    }
  ]
}
